flask_nestify/__init__.py
flask_nestify/body.py
flask_nestify/core.py
flask_nestify/decorator.py
flask_nestify/exception.py
flask_nestify/globals.py
flask_nestify/headers.py
flask_nestify/httpcode.py
flask_nestify/logger.py
flask_nestify/pipe.py
flask_nestify/query.py
flask_nestify/response.py
flask_nestify/unittest.py
flask_nestify/utils.py
flask_nestify-0.2.1.dist-info/METADATA
flask_nestify-0.2.1.dist-info/WHEEL
flask_nestify-0.2.1.dist-info/RECORD
