Metadata-Version: 2.3
Name: flask-nestify
Version: 0.2.1
Summary: 
License: MIT
Author: Ericson Joseph
Author-email: ericsonjoseph@gmail.com
Requires-Python: >=3.10,<4.0
Classifier: License :: OSI Approved :: MIT License
Classifier: Programming Language :: Python :: 3
Classifier: Programming Language :: Python :: 3.10
Classifier: Programming Language :: Python :: 3.11
Classifier: Programming Language :: Python :: 3.12
Classifier: Programming Language :: Python :: 3.13
Requires-Dist: colorama (>=0.4.6,<0.5.0)
Requires-Dist: flasgger (==0.9.7.1)
Requires-Dist: flask (==3.0.3)
